aiomodernforms/__init__.py
aiomodernforms/__version__.py
aiomodernforms/const.py
aiomodernforms/exceptions.py
aiomodernforms/models.py
aiomodernforms/modernforms.py
aiomodernforms-0.1.8.dist-info/LICENSE.md
aiomodernforms-0.1.8.dist-info/METADATA
aiomodernforms-0.1.8.dist-info/WHEEL
aiomodernforms-0.1.8.dist-info/top_level.txt
aiomodernforms-0.1.8.dist-info/RECORD
