Metadata-Version: 2.1
Name: aiomodernforms
Version: 0.1.8
Summary: Asynchronous Python client for Modern Forms fans.
Home-page: https://github.com/wonderslug/aiomodernforms
Author: Brian Towles
Author-email: brian@towles.com
License: MIT license
Keywords: modernforms,api,async,client
Platform: UNKNOWN
Classifier: Development Status :: 4 - Beta
Classifier: Framework :: AsyncIO
Classifier: Intended Audience :: Developers
Classifier: License :: OSI Approved :: MIT License
Classifier: Natural Language :: English
Classifier: Programming Language :: Python :: 3.7
Classifier: Programming Language :: Python :: 3.8
Classifier: Programming Language :: Python :: 3
Classifier: Topic :: Software Development :: Libraries :: Python Modules
Requires-Dist: aiohttp (>=3.0.0)
Requires-Dist: yarl
Requires-Dist: backoff (>=1.9.0)
